latestearthquake/__init__.py
latestearthquake_Indonesia_BMKG-1.0.2.dist-info/LICENSE
latestearthquake_Indonesia_BMKG-1.0.2.dist-info/METADATA
latestearthquake_Indonesia_BMKG-1.0.2.dist-info/WHEEL
latestearthquake_Indonesia_BMKG-1.0.2.dist-info/top_level.txt
latestearthquake_Indonesia_BMKG-1.0.2.dist-info/RECORD
