Metadata-Version: 2.1
Name: latestearthquake-Indonesia-BMKG
Version: 1.0.2
Summary: This package will get the latest earthquake from Indonesia Meteorological, Climatological, and Geophysical Agency (BMKG).
Home-page: https://github.com/RiauTechDev/latest-eartquake-BMKG
Author: Christian Yurianja
Author-email: riautechdev@gmail.com 
License: UNKNOWN
Project-URL: Medium, https://riautechdev.medium.com
Platform: UNKNOWN
Classifier: Programming Language :: Python :: 3
Classifier: License :: OSI Approved :: GNU General Public License v3 or later (GPLv3+)
Classifier: Operating System :: OS Independent
Classifier: Development Status :: 5 - Production/Stable
Requires-Python: >=3.6
License-File: LICENSE
Requires-Dist: beautifulsoup4
Requires-Dist: requests
